{
  "id": "room_2_maze_of_bulls",
  "name": "Maze of Bulls",
  "layout": [
    "###############",
    "#.............#",
    "#..#########..#",
    "#..#VVVVVVV#..#",
    "#..#VVVVVVV#..#",
    "#..#VVVVVVV#..#",
    "#..#VVVVVVV#..#",
    "#..#VVVVVVV#..#",
    "#..#########..#",
    "#.............#",
    "#..#########..#",
    "#..#.......#..#",
    "#.............#",
    "#.............#",
    "###############"
  ],
  "spawnPoints": [
    {
      "x": 2,
      "y": 9,
      "enemyType": "bull"
    },
    {
      "x": 12,
      "y": 9,
      "enemyType": "bull"
    }
  ],
  "friendlySpawnPoints": [],
  "obstacles": []
}